easy_allure/__init__.py
easy_allure/allurectl.py
easy_allure/exceptions.py
easy_allure/gitlab.py
easy_allure/helpers.py
easy_allure/logger.py
easy_allure/main.py
easy_allure/testops.py
easy_allure-1.3.0.1212.dist-info/LICENSE
easy_allure-1.3.0.1212.dist-info/METADATA
easy_allure-1.3.0.1212.dist-info/WHEEL
easy_allure-1.3.0.1212.dist-info/entry_points.txt
easy_allure-1.3.0.1212.dist-info/top_level.txt
easy_allure-1.3.0.1212.dist-info/RECORD
