Metadata-Version: 2.1
Name: easy_allure
Version: 1.3.0.1212
Summary: Library for allure testops
Home-page: https://github.com/TeoDV/easy_allure
Author: Polianok Bogdan
Author-email: bogdan.polianok@gmail.com
License: Apache-2.0
Classifier: License :: OSI Approved :: Apache Software License
Classifier: Programming Language :: Python :: 3.7
Classifier: Programming Language :: Python :: 3.8
Classifier: Programming Language :: Python :: 3.9
Classifier: Programming Language :: Python :: 3.10
Requires-Python: >=3.7
License-File: LICENSE
